src/cli.py
csvtodeta-1.3.1.dist-info/LICENSE
csvtodeta-1.3.1.dist-info/METADATA
csvtodeta-1.3.1.dist-info/WHEEL
csvtodeta-1.3.1.dist-info/entry_points.txt
csvtodeta-1.3.1.dist-info/top_level.txt
csvtodeta-1.3.1.dist-info/RECORD
