Metadata-Version: 2.1
Name: csvtodeta
Version: 1.3.1
Summary: A Lightweight tool to upload CSV files data into Deta Base.
Home-page: https://github.com/fredysomy/CsvToDeta
Author: Fredy Somy
Author-email: fredysomy@gmail.com
License: Apache Software License 2.0
Keywords: csv,database,json
Platform: UNKNOWN
Classifier: Development Status :: 2 - Pre-Alpha
Classifier: License :: OSI Approved :: Apache Software License
Classifier: Natural Language :: English
Classifier: Programming Language :: Python :: 3
Requires-Python: >=3
Requires-Dist: fire
Requires-Dist: deta
